{"openapi":"3.1.0","info":{"title":"FastAPI","version":"0.1.0"},"paths":{"/sessions":{"post":{"summary":"Init Session","operationId":"init_session_sessions_post","responses":{"201":{"description":"Successful Response","content":{"application/json":{"schema":{}}}}}}},"/topics":{"post":{"summary":"Set Topics","operationId":"set_topics_topics_post","parameters":[{"name":"session_id","in":"cookie","required":true,"schema":{"type":"string","format":"uuid","title":"Session Id"}}],"requestBody":{"required":true,"content":{"application/json":{"schema":{"$ref":"#/components/schemas/SetTopicsRequestModel"}}}},"responses":{"201":{"description":"Successful Response","content":{"application/json":{"schema":{}}}},"422":{"description":"Validation Error","content":{"application/json":{"schema":{"$ref":"#/components/schemas/HTTPValidationError"}}}}}}},"/radio-streams":{"get":{"summary":"Start Radio Stream","operationId":"start_radio_stream_radio_streams_get","parameters":[{"name":"session_id","in":"cookie","required":true,"schema":{"type":"string","format":"uuid","title":"Session Id"}}],"responses":{"200":{"description":"Successful Response","content":{"application/json":{"schema":{}}}},"422":{"description":"Validation Error","content":{"application/json":{"schema":{"$ref":"#/components/schemas/HTTPValidationError"}}}}}}},"/radio-streams/flow-commands":{"post":{"summary":"Process Flow Command","operationId":"process_flow_command_radio_streams_flow_commands_post","parameters":[{"name":"session_id","in":"cookie","required":true,"schema":{"type":"string","format":"uuid","title":"Session Id"}}],"requestBody":{"required":true,"content":{"application/json":{"schema":{"$ref":"#/components/schemas/ProcessFlowCommandRequestModel"}}}},"responses":{"201":{"description":"Successful Response","content":{"application/json":{"schema":{}}}},"400":{"description":"Failed to recognized flow command"},"422":{"description":"Validation Error","content":{"application/json":{"schema":{"$ref":"#/components/schemas/HTTPValidationError"}}}}}}}},"components":{"schemas":{"HTTPValidationError":{"properties":{"detail":{"items":{"$ref":"#/components/schemas/ValidationError"},"type":"array","title":"Detail"}},"type":"object","title":"HTTPValidationError"},"ProcessFlowCommandRequestModel":{"properties":{"text":{"type":"string","title":"Text"}},"type":"object","required":["text"],"title":"ProcessFlowCommandRequestModel"},"SetTopicsRequestModel":{"properties":{"text":{"type":"string","title":"Text"}},"type":"object","required":["text"],"title":"SetTopicsRequestModel"},"ValidationError":{"properties":{"loc":{"items":{"anyOf":[{"type":"string"},{"type":"integer"}]},"type":"array","title":"Location"},"msg":{"type":"string","title":"Message"},"type":{"type":"string","title":"Error Type"}},"type":"object","required":["loc","msg","type"],"title":"ValidationError"}}}}
